spark_metabase_api/__init__.py
spark_metabase_api/_helper_methods.py
spark_metabase_api/_rest_methods.py
spark_metabase_api/copy_methods.py
spark_metabase_api/create_methods.py
spark_metabase_api/main_methods.py
spark_metabase_api/modify_methods.py
spark_metabase_api-0.1.13.1.dist-info/METADATA
spark_metabase_api-0.1.13.1.dist-info/WHEEL
spark_metabase_api-0.1.13.1.dist-info/top_level.txt
spark_metabase_api-0.1.13.1.dist-info/RECORD
